core_utils_dev/__init__.py
core_utils_dev/decorators.py
core_utils_dev/print_comments.py
core_utils_dev/py.typed
core_utils_dev/requirements_utils.py
turintech_dev_utils-1.0.0a3.dist-info/METADATA
turintech_dev_utils-1.0.0a3.dist-info/WHEEL
turintech_dev_utils-1.0.0a3.dist-info/licenses/LICENSE
turintech_dev_utils-1.0.0a3.dist-info/RECORD
