Metadata-Version: 2.4
Name: turintech_dev_utils
Version: 1.0.0a3
Summary: Developer utilities and tooling
License-Expression: LicenseRef-Turing-Intelligence-Technology-EULA
License-File: LICENSE
Classifier: Development Status :: 5 - Production/Stable
Classifier: License :: Other/Proprietary License
Requires-Python: <3.14,>=3.11
Requires-Dist: turintech-base-utils<3.0.0,>=1.0.0a0
Requires-Dist: turintech-exceptions<3.0.0,>=2.0.0a0
Requires-Dist: turintech-logging<3.0.0,>=2.0.0a0
